<annotation>
	<folder>0</folder>
	<filename>0_443.jpg</filename>
	<path>C:\Users\13234\Desktop\data\0\0_443.jpg</path>
	<source>
		<database>Unknown</database>
	</source>
	<size>
		<width>600</width>
		<height>600</height>
		<depth>3</depth>
	</size>
	<segmented>0</segmented>
	<object>
		<name>Improper medication</name>
		<pose>Unspecified</pose>
		<truncated>0</truncated>
		<difficult>0</difficult>
		<bndbox>
			<xmin>146</xmin>
			<ymin>422</ymin>
			<xmax>296</xmax>
			<ymax>521</ymax>
		</bndbox>
	</object>
	<object>
		<name>Improper medication</name>
		<pose>Unspecified</pose>
		<truncated>0</truncated>
		<difficult>0</difficult>
		<bndbox>
			<xmin>39</xmin>
			<ymin>309</ymin>
			<xmax>122</xmax>
			<ymax>370</ymax>
		</bndbox>
	</object>
	<object>
		<name>Improper medication</name>
		<pose>Unspecified</pose>
		<truncated>0</truncated>
		<difficult>0</difficult>
		<bndbox>
			<xmin>189</xmin>
			<ymin>302</ymin>
			<xmax>260</xmax>
			<ymax>347</ymax>
		</bndbox>
	</object>
	<object>
		<name>Improper medication</name>
		<pose>Unspecified</pose>
		<truncated>0</truncated>
		<difficult>0</difficult>
		<bndbox>
			<xmin>187</xmin>
			<ymin>254</ymin>
			<xmax>253</xmax>
			<ymax>296</ymax>
		</bndbox>
	</object>
	<object>
		<name>Improper medication</name>
		<pose>Unspecified</pose>
		<truncated>0</truncated>
		<difficult>0</difficult>
		<bndbox>
			<xmin>69</xmin>
			<ymin>259</ymin>
			<xmax>156</xmax>
			<ymax>316</ymax>
		</bndbox>
	</object>
	<object>
		<name>Improper medication</name>
		<pose>Unspecified</pose>
		<truncated>0</truncated>
		<difficult>0</difficult>
		<bndbox>
			<xmin>107</xmin>
			<ymin>139</ymin>
			<xmax>239</xmax>
			<ymax>192</ymax>
		</bndbox>
	</object>
	<object>
		<name>Improper medication</name>
		<pose>Unspecified</pose>
		<truncated>0</truncated>
		<difficult>0</difficult>
		<bndbox>
			<xmin>234</xmin>
			<ymin>96</ymin>
			<xmax>354</xmax>
			<ymax>159</ymax>
		</bndbox>
	</object>
	<object>
		<name>Improper medication</name>
		<pose>Unspecified</pose>
		<truncated>0</truncated>
		<difficult>0</difficult>
		<bndbox>
			<xmin>263</xmin>
			<ymin>158</ymin>
			<xmax>408</xmax>
			<ymax>224</ymax>
		</bndbox>
	</object>
	<object>
		<name>Improper medication</name>
		<pose>Unspecified</pose>
		<truncated>0</truncated>
		<difficult>0</difficult>
		<bndbox>
			<xmin>501</xmin>
			<ymin>361</ymin>
			<xmax>575</xmax>
			<ymax>418</ymax>
		</bndbox>
	</object>
	<object>
		<name>Improper medication</name>
		<pose>Unspecified</pose>
		<truncated>0</truncated>
		<difficult>0</difficult>
		<bndbox>
			<xmin>450</xmin>
			<ymin>291</ymin>
			<xmax>533</xmax>
			<ymax>344</ymax>
		</bndbox>
	</object>
	<object>
		<name>Improper medication</name>
		<pose>Unspecified</pose>
		<truncated>0</truncated>
		<difficult>0</difficult>
		<bndbox>
			<xmin>410</xmin>
			<ymin>312</ymin>
			<xmax>488</xmax>
			<ymax>377</ymax>
		</bndbox>
	</object>
	<object>
		<name>Improper medication</name>
		<pose>Unspecified</pose>
		<truncated>0</truncated>
		<difficult>0</difficult>
		<bndbox>
			<xmin>441</xmin>
			<ymin>377</ymin>
			<xmax>557</xmax>
			<ymax>503</ymax>
		</bndbox>
	</object>
</annotation>
