<annotation verified="yes">
	<folder>1</folder>
	<filename>1_482.jpg</filename>
	<path>C:\Users\13234\Desktop\data2\1\1_482.jpg</path>
	<source>
		<database>Unknown</database>
	</source>
	<size>
		<width>600</width>
		<height>600</height>
		<depth>3</depth>
	</size>
	<segmented>0</segmented>
	<object>
		<name>blight</name>
		<pose>Unspecified</pose>
		<truncated>0</truncated>
		<difficult>0</difficult>
		<bndbox>
			<xmin>97</xmin>
			<ymin>354</ymin>
			<xmax>275</xmax>
			<ymax>479</ymax>
		</bndbox>
	</object>
</annotation>
